LICENSE.txt
MANIFEST.in
README.md
setup.cfg
setup.py
mysql_partition_rotator/DateHelper.py
mysql_partition_rotator/Partition.py
mysql_partition_rotator/PartitionRotator.py
mysql_partition_rotator/RotateDaily.py
mysql_partition_rotator/RotateHourly.py
mysql_partition_rotator/RotateMonthly.py
mysql_partition_rotator/__init__.py
mysql_partition_rotator.egg-info/PKG-INFO
mysql_partition_rotator.egg-info/SOURCES.txt
mysql_partition_rotator.egg-info/dependency_links.txt
mysql_partition_rotator.egg-info/requires.txt
mysql_partition_rotator.egg-info/top_level.txt