Metadata-Version: 2.1
Name: mysql-partition-rotator
Version: 0.3
Summary: Rotates mysql tables by using partition method
Home-page: https://github.com/jinraynor1/mysql_partition_rotator
Author: Jimmy Atauje
Author-email: jimmy.atauje@gmail.com
License: MIT
Download-URL: https://github.com/jinraynor1/mysql_partition_rotator/releases/tag/v0.3-alpha
Keywords: mysql,partition,rotate,python
Platform: UNKNOWN
Classifier: Development Status :: 3 - Alpha
Classifier: Intended Audience :: Developers
Classifier: Topic :: Software Development :: Build Tools
Classifier: License :: OSI Approved :: MIT License
Classifier: Programming Language :: Python :: 3
Classifier: Programming Language :: Python :: 3.4
Classifier: Programming Language :: Python :: 3.5
Classifier: Programming Language :: Python :: 3.6
License-File: LICENSE.txt
